baktfold/__init__.py
baktfold/bakta/annotation.py
baktfold/bakta/config.py
baktfold/bakta/constants.py
baktfold/bakta/pstc.py
baktfold/bakta/so.py
baktfold/cnn/cnn_chkpnt/model.pt
baktfold/databases/db.py
baktfold/features/create_foldseek_db.py
baktfold/features/predict_3Di.py
baktfold/features/run_foldseek.py
baktfold/io/__init__.py
baktfold/io/fasta.py
baktfold/io/fasta_in.py
baktfold/io/gff.py
baktfold/io/handle_genbank.py
baktfold/io/insdc.py
baktfold/io/io.py
baktfold/io/json.py
baktfold/io/json_in.py
baktfold/io/tsv.py
baktfold/results/tophit.py
baktfold/subcommands/compare.py
baktfold/subcommands/predict.py
baktfold/utils/CITATION
baktfold/utils/VERSION
baktfold/utils/constants.py
baktfold/utils/external_tools.py
baktfold/utils/util.py
baktfold/utils/validation.py
baktfold-0.0.3.dist-info/licenses/LICENSE
baktfold-0.0.3.dist-info/METADATA
baktfold-0.0.3.dist-info/WHEEL
baktfold-0.0.3.dist-info/entry_points.txt
baktfold-0.0.3.dist-info/top_level.txt
baktfold-0.0.3.dist-info/zip-safe
baktfold-0.0.3.dist-info/RECORD
